odoo8_addon_stock_scanner-8.0.1.0.0.99.dev38-py3.8-nspkg.pth
odoo_addons/stock_scanner/README.rst
odoo_addons/stock_scanner/__init__.py
odoo_addons/stock_scanner/__openerp__.py
odoo_addons/stock_scanner/load_scenario.py
odoo_addons/stock_scanner/data/ir_cron.xml
odoo_addons/stock_scanner/data/stock_scanner.xml
odoo_addons/stock_scanner/data/scenarios/Login/Login.scenario
odoo_addons/stock_scanner/data/scenarios/Login/stock_scanner.scanner_scenario_login_step_done.py
odoo_addons/stock_scanner/data/scenarios/Login/stock_scanner.scanner_scenario_login_step_error.py
odoo_addons/stock_scanner/data/scenarios/Login/stock_scanner.scanner_scenario_login_step_login.py
odoo_addons/stock_scanner/data/scenarios/Login/stock_scanner.scanner_scenario_login_step_pwd.py
odoo_addons/stock_scanner/data/scenarios/Logout/Logout.scenario
odoo_addons/stock_scanner/data/scenarios/Logout/stock_scanner.scanner_scenario_logout_step_cancelled.py
odoo_addons/stock_scanner/data/scenarios/Logout/stock_scanner.scanner_scenario_logout_step_confirm.py
odoo_addons/stock_scanner/data/scenarios/Logout/stock_scanner.scanner_scenario_logout_step_confirmed.py
odoo_addons/stock_scanner/demo/stock_scanner_demo.xml
odoo_addons/stock_scanner/demo/Tutorial/Tutorial.scenario
odoo_addons/stock_scanner/demo/Tutorial/Sentinel/Sentinel.scenario
odoo_addons/stock_scanner/demo/Tutorial/Sentinel/scanner_scenario_step_sentinel_going_back.py
odoo_addons/stock_scanner/demo/Tutorial/Sentinel/scanner_scenario_step_sentinel_introduction.py
odoo_addons/stock_scanner/demo/Tutorial/Sentinel/scanner_scenario_step_sentinel_list_scrolling.py
odoo_addons/stock_scanner/demo/Tutorial/Sentinel/scanner_scenario_step_sentinel_return_values.py
odoo_addons/stock_scanner/demo/Tutorial/Sentinel/scanner_scenario_step_sentinel_scrolling.py
odoo_addons/stock_scanner/demo/Tutorial/Step_types/Step_types.scenario
odoo_addons/stock_scanner/demo/Tutorial/Step_types/scanner_scenario_step_step_types_confirm.py
odoo8_addon_stock_scanner-8.0.1.0.0.99.dev38.dist-info/METADATA
odoo8_addon_stock_scanner-8.0.1.0.0.99.dev38.dist-info/WHEEL
odoo8_addon_stock_scanner-8.0.1.0.0.99.dev38.dist-info/namespace_packages.txt
odoo8_addon_stock_scanner-8.0.1.0.0.99.dev38.dist-info/top_level.txt
odoo8_addon_stock_scanner-8.0.1.0.0.99.dev38.dist-info/RECORD
